netsdldv/__init__.py
netsdldv/dv_manager.py
netsdldv/adapter/__init__.py
netsdldv/adapter/base_adapter.py
netsdldv/adapter/sql_server.py
netsdldv/factory/__init__.py
netsdldv/factory/dv_db_loader.py
netsdldv/factory/dv_factory.py
netsdldv/factory/dv_xml_factory.py
netsdldv/models/Condition.py
netsdldv/models/Field.py
netsdldv/models/Filter.py
netsdldv/models/Operator.py
netsdldv/models/Relation.py
netsdldv/models/Table.py
netsdldv/models/__init__.py
netsdldv/tools/__init__.py
netsdldv/tools/dv2xml.py
netsdldv-0.0.9.dist-info/METADATA
netsdldv-0.0.9.dist-info/WHEEL
netsdldv-0.0.9.dist-info/top_level.txt
netsdldv-0.0.9.dist-info/RECORD
