Metadata-Version: 2.1
Name: netsdldv
Version: 0.0.9
Summary: a tools for ami
Home-page: https://git.netsdl.com/dv/DvManager
Author: codmowa
Author-email: chenchu@netsdl.com
License: MIT
Keywords: ami dv python
Platform: UNKNOWN
Requires-Dist: pyodbc (>=4.0.27)
Requires-Dist: SQLAlchemy (>=1.3.11)
